awsdsc/__init__.py
awsdsc/exception.py
awsdsc/main.py
awsdsc/processor.py
awsdsc-0.2.10.dist-info/METADATA
awsdsc-0.2.10.dist-info/WHEEL
awsdsc-0.2.10.dist-info/entry_points.txt
awsdsc-0.2.10.dist-info/top_level.txt
awsdsc-0.2.10.dist-info/RECORD
