Metadata-Version: 2.1
Name: awsdsc
Version: 0.2.10
Summary: AWS universal describe command
Author: Takatoshi Iwasa
Author-email: ap.gr.le@gmail.com
License: UNKNOWN
Platform: UNKNOWN
Requires-Dist: click (~=8.0.3)
Requires-Dist: boto3 (~=1.20.7)
Requires-Dist: PyYAML (~=6.0)
Requires-Dist: prompt-toolkit (~=3.0.24)
Requires-Dist: Pygments (~=2.10.0)
